[
  {
    "id": 1,
    "vendorId": 31,
    "name": "Шведский стол",
    "category": "Кейтеринг",
    "description": "Профессиональная услуга \"Фуршет на 50 человек\" от опытных специалистов",
    "priceMin": 18363,
    "priceMax": 69933,
    "unit": "за человека",
    "duration": 6,
    "createdAt": "2023-03-06T21:00:00.000Z"
  },
  {
    "id": 2,
    "vendorId": 31,
    "name": "Шведский стол",
    "category": "Кейтеринг",
    "description": "Профессиональная услуга \"Кофе-брейк\" от опытных специалистов",
    "priceMin": 5459,
    "priceMax": 127370,
    "unit": "за человека",
    "duration": 7,
    "createdAt": "2023-07-22T21:00:00.000Z"
  },
  {
    "id": 3,
    "vendorId": 32,
    "name": "Освещение",
    "category": "Декор",
    "description": "Профессиональная услуга \"Цветочная арка\" от опытных специалистов",
    "priceMin": 31709,
    "priceMax": 65836,
    "unit": "за услугу",
    "duration": 7,
    "createdAt": "2023-12-13T21:00:00.000Z"
  },
  {
    "id": 4,
    "vendorId": 32,
    "name": "Свечи",
    "category": "Декор",
    "description": "Профессиональная услуга \"Фотозона\" от опытных специалистов",
    "priceMin": 53436,
    "priceMax": 167721,
    "unit": "за человека",
    "duration": 8,
    "createdAt": "2023-01-14T21:00:00.000Z"
  },
  {
    "id": 5,
    "vendorId": 32,
    "name": "Оформление зала",
    "category": "Декор",
    "description": "Профессиональная услуга \"Свечи\" от опытных специалистов",
    "priceMin": 47818,
    "priceMax": 116924,
    "unit": "за час",
    "duration": 3,
    "createdAt": "2023-04-22T21:00:00.000Z"
  },
  {
    "id": 6,
    "vendorId": 33,
    "name": "Фото-видео зона",
    "category": "Развлечения",
    "description": "Профессиональная услуга \"Фото-видео зона\" от опытных специалистов",
    "priceMin": 19953,
    "priceMax": 200727,
    "unit": "за человека",
    "duration": 2,
    "createdAt": "2023-07-23T21:00:00.000Z"
  },
  {
    "id": 7,
    "vendorId": 33,
    "name": "Шоу-программа",
    "category": "Развлечения",
    "description": "Профессиональная услуга \"Фото-видео зона\" от опытных специалистов",
    "priceMin": 16798,
    "priceMax": 229127,
    "unit": "за час",
    "duration": 9,
    "createdAt": "2023-01-20T21:00:00.000Z"
  },
  {
    "id": 8,
    "vendorId": 33,
    "name": "Квест",
    "category": "Развлечения",
    "description": "Профессиональная услуга \"Живая музыка\" от опытных специалистов",
    "priceMin": 33379,
    "priceMax": 187792,
    "unit": "за человека",
    "duration": 6,
    "createdAt": "2023-01-19T21:00:00.000Z"
  },
  {
    "id": 9,
    "vendorId": 34,
    "name": "Живая музыка",
    "category": "Развлечения",
    "description": "Профессиональная услуга \"Фото-видео зона\" от опытных специалистов",
    "priceMin": 17775,
    "priceMax": 204657,
    "unit": "за услугу",
    "duration": 5,
    "createdAt": "2023-06-15T21:00:00.000Z"
  },
  {
    "id": 10,
    "vendorId": 34,
    "name": "Шоу-программа",
    "category": "Развлечения",
    "description": "Профессиональная услуга \"Аниматоры\" от опытных специалистов",
    "priceMin": 15914,
    "priceMax": 161154,
    "unit": "за человека",
    "duration": 6,
    "createdAt": "2023-08-15T21:00:00.000Z"
  },
  {
    "id": 11,
    "vendorId": 34,
    "name": "Аниматоры",
    "category": "Развлечения",
    "description": "Профессиональная услуга \"Фото-видео зона\" от опытных специалистов",
    "priceMin": 10009,
    "priceMax": 231107,
    "unit": "за час",
    "duration": 6,
    "createdAt": "2023-03-11T21:00:00.000Z"
  },
  {
    "id": 12,
    "vendorId": 35,
    "name": "Корпоративный обед",
    "category": "Кейтеринг",
    "description": "Профессиональная услуга \"Кофе-брейк\" от опытных специалистов",
    "priceMin": 52332,
    "priceMax": 221972,
    "unit": "за час",
    "duration": 4,
    "createdAt": "2023-09-08T21:00:00.000Z"
  },
  {
    "id": 13,
    "vendorId": 35,
    "name": "Банкет на 100 человек",
    "category": "Кейтеринг",
    "description": "Профессиональная услуга \"Банкет на 100 человек\" от опытных специалистов",
    "priceMin": 7766,
    "priceMax": 155838,
    "unit": "за мероприятие",
    "duration": 8,
    "createdAt": "2023-10-10T21:00:00.000Z"
  },
  {
    "id": 14,
    "vendorId": 35,
    "name": "Свадебный банкет",
    "category": "Кейтеринг",
    "description": "Профессиональная услуга \"Фуршет на 50 человек\" от опытных специалистов",
    "priceMin": 18213,
    "priceMax": 90542,
    "unit": "за час",
    "duration": 9,
    "createdAt": "2023-06-30T21:00:00.000Z"
  },
  {
    "id": 15,
    "vendorId": 35,
    "name": "Канapé-сервис",
    "category": "Кейтеринг",
    "description": "Профессиональная услуга \"Барбекю\" от опытных специалистов",
    "priceMin": 19955,
    "priceMax": 178174,
    "unit": "за час",
    "duration": 9,
    "createdAt": "2023-05-06T21:00:00.000Z"
  },
  {
    "id": 16,
    "vendorId": 36,
    "name": "Детская съемка",
    "category": "Фото и видео",
    "description": "Профессиональная услуга \"Корпоративная съемка\" от опытных специалистов",
    "priceMin": 10485,
    "priceMax": 63892,
    "unit": "за мероприятие",
    "duration": 2,
    "createdAt": "2023-01-02T21:00:00.000Z"
  },
  {
    "id": 17,
    "vendorId": 36,
    "name": "Портретная съемка",
    "category": "Фото и видео",
    "description": "Профессиональная услуга \"Корпоративная съемка\" от опытных специалистов",
    "priceMin": 40286,
    "priceMax": 239313,
    "unit": "за мероприятие",
    "duration": 6,
    "createdAt": "2023-09-19T21:00:00.000Z"
  },
  {
    "id": 18,
    "vendorId": 36,
    "name": "Love Story",
    "category": "Фото и видео",
    "description": "Профессиональная услуга \"Детская съемка\" от опытных специалистов",
    "priceMin": 46832,
    "priceMax": 83071,
    "unit": "за услугу",
    "duration": 5,
    "createdAt": "2023-09-11T21:00:00.000Z"
  },
  {
    "id": 19,
    "vendorId": 37,
    "name": "Экскурсионный автобус",
    "category": "Транспорт",
    "description": "Профессиональная услуга \"Автобус\" от опытных специалистов",
    "priceMin": 14458,
    "priceMax": 158249,
    "unit": "за мероприятие",
    "duration": 7,
    "createdAt": "2023-02-21T21:00:00.000Z"
  },
  {
    "id": 20,
    "vendorId": 37,
    "name": "Свадебный кортеж",
    "category": "Транспорт",
    "description": "Профессиональная услуга \"VIP транспорт\" от опытных специалистов",
    "priceMin": 31392,
    "priceMax": 107766,
    "unit": "за час",
    "duration": 6,
    "createdAt": "2023-12-04T21:00:00.000Z"
  },
  {
    "id": 21,
    "vendorId": 38,
    "name": "Репортажная съемка",
    "category": "Фото и видео",
    "description": "Профессиональная услуга \"Промо-ролик\" от опытных специалистов",
    "priceMin": 37799,
    "priceMax": 192487,
    "unit": "за мероприятие",
    "duration": 8,
    "createdAt": "2023-02-18T21:00:00.000Z"
  },
  {
    "id": 22,
    "vendorId": 38,
    "name": "Love Story",
    "category": "Фото и видео",
    "description": "Профессиональная услуга \"Репортажная съемка\" от опытных специалистов",
    "priceMin": 17408,
    "priceMax": 130845,
    "unit": "за мероприятие",
    "duration": 5,
    "createdAt": "2023-11-08T21:00:00.000Z"
  },
  {
    "id": 23,
    "vendorId": 38,
    "name": "Портретная съемка",
    "category": "Фото и видео",
    "description": "Профессиональная услуга \"Love Story\" от опытных специалистов",
    "priceMin": 27579,
    "priceMax": 246042,
    "unit": "за услугу",
    "duration": 9,
    "createdAt": "2023-01-08T21:00:00.000Z"
  },
  {
    "id": 24,
    "vendorId": 38,
    "name": "Love Story",
    "category": "Фото и видео",
    "description": "Профессиональная услуга \"Портретная съемка\" от опытных специалистов",
    "priceMin": 38316,
    "priceMax": 91122,
    "unit": "за час",
    "duration": 3,
    "createdAt": "2023-12-16T21:00:00.000Z"
  },
  {
    "id": 25,
    "vendorId": 39,
    "name": "Love Story",
    "category": "Фото и видео",
    "description": "Профессиональная услуга \"Репортажная съемка\" от опытных специалистов",
    "priceMin": 51897,
    "priceMax": 192709,
    "unit": "за человека",
    "duration": 6,
    "createdAt": "2023-07-01T21:00:00.000Z"
  },
  {
    "id": 26,
    "vendorId": 39,
    "name": "Корпоративная съемка",
    "category": "Фото и видео",
    "description": "Профессиональная услуга \"Свадебная съемка\" от опытных специалистов",
    "priceMin": 52940,
    "priceMax": 201488,
    "unit": "за час",
    "duration": 2,
    "createdAt": "2023-06-25T21:00:00.000Z"
  },
  {
    "id": 27,
    "vendorId": 39,
    "name": "Репортажная съемка",
    "category": "Фото и видео",
    "description": "Профессиональная услуга \"Love Story\" от опытных специалистов",
    "priceMin": 21650,
    "priceMax": 226229,
    "unit": "за человека",
    "duration": 4,
    "createdAt": "2023-06-18T21:00:00.000Z"
  },
  {
    "id": 28,
    "vendorId": 40,
    "name": "VIP транспорт",
    "category": "Транспорт",
    "description": "Профессиональная услуга \"Микроавтобус\" от опытных специалистов",
    "priceMin": 29828,
    "priceMax": 188864,
    "unit": "за услугу",
    "duration": 3,
    "createdAt": "2023-07-24T21:00:00.000Z"
  },
  {
    "id": 29,
    "vendorId": 40,
    "name": "Лимузин",
    "category": "Транспорт",
    "description": "Профессиональная услуга \"Экскурсионный автобус\" от опытных специалистов",
    "priceMin": 29606,
    "priceMax": 122066,
    "unit": "за мероприятие",
    "duration": 3,
    "createdAt": "2023-07-25T21:00:00.000Z"
  },
  {
    "id": 30,
    "vendorId": 41,
    "name": "Аниматоры",
    "category": "Развлечения",
    "description": "Профессиональная услуга \"Ведущий\" от опытных специалистов",
    "priceMin": 16186,
    "priceMax": 151718,
    "unit": "за час",
    "duration": 8,
    "createdAt": "2023-01-25T21:00:00.000Z"
  },
  {
    "id": 31,
    "vendorId": 41,
    "name": "Квест",
    "category": "Развлечения",
    "description": "Профессиональная услуга \"Аниматоры\" от опытных специалистов",
    "priceMin": 30451,
    "priceMax": 53163,
    "unit": "за мероприятие",
    "duration": 4,
    "createdAt": "2023-10-24T21:00:00.000Z"
  },
  {
    "id": 32,
    "vendorId": 41,
    "name": "Фото-видео зона",
    "category": "Развлечения",
    "description": "Профессиональная услуга \"Фото-видео зона\" от опытных специалистов",
    "priceMin": 7537,
    "priceMax": 138049,
    "unit": "за час",
    "duration": 9,
    "createdAt": "2023-04-21T21:00:00.000Z"
  },
  {
    "id": 33,
    "vendorId": 42,
    "name": "Микроавтобус",
    "category": "Транспорт",
    "description": "Профессиональная услуга \"Лимузин\" от опытных специалистов",
    "priceMin": 39584,
    "priceMax": 193755,
    "unit": "за мероприятие",
    "duration": 6,
    "createdAt": "2023-06-18T21:00:00.000Z"
  },
  {
    "id": 34,
    "vendorId": 42,
    "name": "Свадебный кортеж",
    "category": "Транспорт",
    "description": "Профессиональная услуга \"Экскурсионный автобус\" от опытных специалистов",
    "priceMin": 30779,
    "priceMax": 51895,
    "unit": "за мероприятие",
    "duration": 3,
    "createdAt": "2023-03-03T21:00:00.000Z"
  },
  {
    "id": 35,
    "vendorId": 43,
    "name": "Микроавтобус",
    "category": "Транспорт",
    "description": "Профессиональная услуга \"Микроавтобус\" от опытных специалистов",
    "priceMin": 8621,
    "priceMax": 144715,
    "unit": "за услугу",
    "duration": 2,
    "createdAt": "2023-08-15T21:00:00.000Z"
  },
  {
    "id": 36,
    "vendorId": 43,
    "name": "Автобус",
    "category": "Транспорт",
    "description": "Профессиональная услуга \"VIP транспорт\" от опытных специалистов",
    "priceMin": 5085,
    "priceMax": 52468,
    "unit": "за человека",
    "duration": 2,
    "createdAt": "2023-07-13T21:00:00.000Z"
  },
  {
    "id": 37,
    "vendorId": 44,
    "name": "Свадебный банкет",
    "category": "Кейтеринг",
    "description": "Профессиональная услуга \"Фуршет на 50 человек\" от опытных специалистов",
    "priceMin": 19965,
    "priceMax": 160620,
    "unit": "за человека",
    "duration": 3,
    "createdAt": "2023-08-26T21:00:00.000Z"
  },
  {
    "id": 38,
    "vendorId": 44,
    "name": "Барбекю",
    "category": "Кейтеринг",
    "description": "Профессиональная услуга \"Канapé-сервис\" от опытных специалистов",
    "priceMin": 7846,
    "priceMax": 236810,
    "unit": "за человека",
    "duration": 7,
    "createdAt": "2023-01-27T21:00:00.000Z"
  },
  {
    "id": 39,
    "vendorId": 44,
    "name": "Канapé-сервис",
    "category": "Кейтеринг",
    "description": "Профессиональная услуга \"Фуршет на 50 человек\" от опытных специалистов",
    "priceMin": 32435,
    "priceMax": 106316,
    "unit": "за услугу",
    "duration": 6,
    "createdAt": "2023-11-10T21:00:00.000Z"
  },
  {
    "id": 40,
    "vendorId": 45,
    "name": "Ведущий",
    "category": "Развлечения",
    "description": "Профессиональная услуга \"Квест\" от опытных специалистов",
    "priceMin": 46472,
    "priceMax": 66132,
    "unit": "за мероприятие",
    "duration": 8,
    "createdAt": "2023-03-13T21:00:00.000Z"
  },
  {
    "id": 41,
    "vendorId": 45,
    "name": "Фото-видео зона",
    "category": "Развлечения",
    "description": "Профессиональная услуга \"Шоу-программа\" от опытных специалистов",
    "priceMin": 19884,
    "priceMax": 77328,
    "unit": "за мероприятие",
    "duration": 7,
    "createdAt": "2023-10-10T21:00:00.000Z"
  },
  {
    "id": 42,
    "vendorId": 46,
    "name": "Корпоративный обед",
    "category": "Кейтеринг",
    "description": "Профессиональная услуга \"Кофе-брейк\" от опытных специалистов",
    "priceMin": 14090,
    "priceMax": 210988,
    "unit": "за мероприятие",
    "duration": 6,
    "createdAt": "2023-01-18T21:00:00.000Z"
  },
  {
    "id": 43,
    "vendorId": 46,
    "name": "Банкет на 100 человек",
    "category": "Кейтеринг",
    "description": "Профессиональная услуга \"Корпоративный обед\" от опытных специалистов",
    "priceMin": 7345,
    "priceMax": 156339,
    "unit": "за человека",
    "duration": 2,
    "createdAt": "2023-02-25T21:00:00.000Z"
  },
  {
    "id": 44,
    "vendorId": 47,
    "name": "Портретная съемка",
    "category": "Фото и видео",
    "description": "Профессиональная услуга \"Детская съемка\" от опытных специалистов",
    "priceMin": 40837,
    "priceMax": 91507,
    "unit": "за человека",
    "duration": 9,
    "createdAt": "2023-09-12T21:00:00.000Z"
  },
  {
    "id": 45,
    "vendorId": 47,
    "name": "Репортажная съемка",
    "category": "Фото и видео",
    "description": "Профессиональная услуга \"Портретная съемка\" от опытных специалистов",
    "priceMin": 35013,
    "priceMax": 246741,
    "unit": "за услугу",
    "duration": 3,
    "createdAt": "2023-06-01T21:00:00.000Z"
  },
  {
    "id": 46,
    "vendorId": 47,
    "name": "Портретная съемка",
    "category": "Фото и видео",
    "description": "Профессиональная услуга \"Свадебная съемка\" от опытных специалистов",
    "priceMin": 41757,
    "priceMax": 74438,
    "unit": "за услугу",
    "duration": 8,
    "createdAt": "2023-06-30T21:00:00.000Z"
  },
  {
    "id": 47,
    "vendorId": 48,
    "name": "Оформление зала",
    "category": "Декор",
    "description": "Профессиональная услуга \"Текстиль\" от опытных специалистов",
    "priceMin": 15492,
    "priceMax": 67056,
    "unit": "за мероприятие",
    "duration": 4,
    "createdAt": "2023-03-31T21:00:00.000Z"
  },
  {
    "id": 48,
    "vendorId": 48,
    "name": "Свечи",
    "category": "Декор",
    "description": "Профессиональная услуга \"Фотозона\" от опытных специалистов",
    "priceMin": 35764,
    "priceMax": 235574,
    "unit": "за час",
    "duration": 3,
    "createdAt": "2023-12-13T21:00:00.000Z"
  },
  {
    "id": 49,
    "vendorId": 48,
    "name": "Цветочная арка",
    "category": "Декор",
    "description": "Профессиональная услуга \"Освещение\" от опытных специалистов",
    "priceMin": 49683,
    "priceMax": 231352,
    "unit": "за мероприятие",
    "duration": 7,
    "createdAt": "2023-02-03T21:00:00.000Z"
  },
  {
    "id": 50,
    "vendorId": 48,
    "name": "Текстиль",
    "category": "Декор",
    "description": "Профессиональная услуга \"Баннеры\" от опытных специалистов",
    "priceMin": 18387,
    "priceMax": 164803,
    "unit": "за услугу",
    "duration": 9,
    "createdAt": "2023-11-20T21:00:00.000Z"
  },
  {
    "id": 51,
    "vendorId": 49,
    "name": "Живая музыка",
    "category": "Развлечения",
    "description": "Профессиональная услуга \"Караоке\" от опытных специалистов",
    "priceMin": 25634,
    "priceMax": 218358,
    "unit": "за мероприятие",
    "duration": 3,
    "createdAt": "2023-04-16T21:00:00.000Z"
  },
  {
    "id": 52,
    "vendorId": 49,
    "name": "Аниматоры",
    "category": "Развлечения",
    "description": "Профессиональная услуга \"Квест\" от опытных специалистов",
    "priceMin": 16424,
    "priceMax": 192021,
    "unit": "за человека",
    "duration": 7,
    "createdAt": "2023-08-31T21:00:00.000Z"
  },
  {
    "id": 53,
    "vendorId": 49,
    "name": "Караоке",
    "category": "Развлечения",
    "description": "Профессиональная услуга \"Ведущий\" от опытных специалистов",
    "priceMin": 21036,
    "priceMax": 245380,
    "unit": "за час",
    "duration": 9,
    "createdAt": "2023-06-11T21:00:00.000Z"
  },
  {
    "id": 54,
    "vendorId": 50,
    "name": "Портретная съемка",
    "category": "Фото и видео",
    "description": "Профессиональная услуга \"Свадебная съемка\" от опытных специалистов",
    "priceMin": 35095,
    "priceMax": 163024,
    "unit": "за услугу",
    "duration": 4,
    "createdAt": "2023-10-31T21:00:00.000Z"
  },
  {
    "id": 55,
    "vendorId": 50,
    "name": "Корпоративная съемка",
    "category": "Фото и видео",
    "description": "Профессиональная услуга \"Промо-ролик\" от опытных специалистов",
    "priceMin": 50387,
    "priceMax": 245225,
    "unit": "за человека",
    "duration": 9,
    "createdAt": "2023-04-19T21:00:00.000Z"
  },
  {
    "id": 56,
    "vendorId": 51,
    "name": "Корпоративная съемка",
    "category": "Фото и видео",
    "description": "Профессиональная услуга \"Детская съемка\" от опытных специалистов",
    "priceMin": 31857,
    "priceMax": 182457,
    "unit": "за человека",
    "duration": 9,
    "createdAt": "2023-03-05T21:00:00.000Z"
  },
  {
    "id": 57,
    "vendorId": 51,
    "name": "Детская съемка",
    "category": "Фото и видео",
    "description": "Профессиональная услуга \"Детская съемка\" от опытных специалистов",
    "priceMin": 14062,
    "priceMax": 225506,
    "unit": "за человека",
    "duration": 3,
    "createdAt": "2023-06-20T21:00:00.000Z"
  },
  {
    "id": 58,
    "vendorId": 51,
    "name": "Видеоклип",
    "category": "Фото и видео",
    "description": "Профессиональная услуга \"Корпоративная съемка\" от опытных специалистов",
    "priceMin": 49953,
    "priceMax": 111582,
    "unit": "за час",
    "duration": 8,
    "createdAt": "2023-02-18T21:00:00.000Z"
  },
  {
    "id": 59,
    "vendorId": 51,
    "name": "Свадебная съемка",
    "category": "Фото и видео",
    "description": "Профессиональная услуга \"Детская съемка\" от опытных специалистов",
    "priceMin": 52237,
    "priceMax": 160871,
    "unit": "за час",
    "duration": 3,
    "createdAt": "2023-09-05T21:00:00.000Z"
  },
  {
    "id": 60,
    "vendorId": 52,
    "name": "Оформление зала",
    "category": "Декор",
    "description": "Профессиональная услуга \"Освещение\" от опытных специалистов",
    "priceMin": 47509,
    "priceMax": 187480,
    "unit": "за час",
    "duration": 4,
    "createdAt": "2023-10-09T21:00:00.000Z"
  },
  {
    "id": 61,
    "vendorId": 52,
    "name": "Свечи",
    "category": "Декор",
    "description": "Профессиональная услуга \"Фотозона\" от опытных специалистов",
    "priceMin": 39614,
    "priceMax": 224484,
    "unit": "за человека",
    "duration": 2,
    "createdAt": "2023-06-23T21:00:00.000Z"
  },
  {
    "id": 62,
    "vendorId": 52,
    "name": "Свечи",
    "category": "Декор",
    "description": "Профессиональная услуга \"Свечи\" от опытных специалистов",
    "priceMin": 27365,
    "priceMax": 163603,
    "unit": "за человека",
    "duration": 5,
    "createdAt": "2023-05-13T21:00:00.000Z"
  },
  {
    "id": 63,
    "vendorId": 52,
    "name": "Оформление зала",
    "category": "Декор",
    "description": "Профессиональная услуга \"Свечи\" от опытных специалистов",
    "priceMin": 16196,
    "priceMax": 105688,
    "unit": "за человека",
    "duration": 6,
    "createdAt": "2023-02-23T21:00:00.000Z"
  },
  {
    "id": 64,
    "vendorId": 53,
    "name": "Барбекю",
    "category": "Кейтеринг",
    "description": "Профессиональная услуга \"Фуршет на 50 человек\" от опытных специалистов",
    "priceMin": 6486,
    "priceMax": 235266,
    "unit": "за человека",
    "duration": 5,
    "createdAt": "2023-01-22T21:00:00.000Z"
  },
  {
    "id": 65,
    "vendorId": 53,
    "name": "Корпоративный обед",
    "category": "Кейтеринг",
    "description": "Профессиональная услуга \"Шведский стол\" от опытных специалистов",
    "priceMin": 27935,
    "priceMax": 227797,
    "unit": "за услугу",
    "duration": 9,
    "createdAt": "2023-04-22T21:00:00.000Z"
  },
  {
    "id": 66,
    "vendorId": 54,
    "name": "Портретная съемка",
    "category": "Фото и видео",
    "description": "Профессиональная услуга \"Корпоративная съемка\" от опытных специалистов",
    "priceMin": 47665,
    "priceMax": 176588,
    "unit": "за услугу",
    "duration": 6,
    "createdAt": "2023-04-03T21:00:00.000Z"
  },
  {
    "id": 67,
    "vendorId": 54,
    "name": "Корпоративная съемка",
    "category": "Фото и видео",
    "description": "Профессиональная услуга \"Репортажная съемка\" от опытных специалистов",
    "priceMin": 44474,
    "priceMax": 121411,
    "unit": "за услугу",
    "duration": 3,
    "createdAt": "2023-12-17T21:00:00.000Z"
  },
  {
    "id": 68,
    "vendorId": 54,
    "name": "Репортажная съемка",
    "category": "Фото и видео",
    "description": "Профессиональная услуга \"Свадебная съемка\" от опытных специалистов",
    "priceMin": 48499,
    "priceMax": 178233,
    "unit": "за услугу",
    "duration": 4,
    "createdAt": "2023-08-09T21:00:00.000Z"
  },
  {
    "id": 69,
    "vendorId": 54,
    "name": "Портретная съемка",
    "category": "Фото и видео",
    "description": "Профессиональная услуга \"Love Story\" от опытных специалистов",
    "priceMin": 8712,
    "priceMax": 192792,
    "unit": "за мероприятие",
    "duration": 6,
    "createdAt": "2023-09-07T21:00:00.000Z"
  },
  {
    "id": 70,
    "vendorId": 55,
    "name": "Свечи",
    "category": "Декор",
    "description": "Профессиональная услуга \"Оформление зала\" от опытных специалистов",
    "priceMin": 39284,
    "priceMax": 182440,
    "unit": "за услугу",
    "duration": 9,
    "createdAt": "2023-07-23T21:00:00.000Z"
  },
  {
    "id": 71,
    "vendorId": 55,
    "name": "Свадебная арка",
    "category": "Декор",
    "description": "Профессиональная услуга \"Текстиль\" от опытных специалистов",
    "priceMin": 33990,
    "priceMax": 249486,
    "unit": "за мероприятие",
    "duration": 6,
    "createdAt": "2023-02-20T21:00:00.000Z"
  },
  {
    "id": 72,
    "vendorId": 55,
    "name": "Баннеры",
    "category": "Декор",
    "description": "Профессиональная услуга \"Цветочная арка\" от опытных специалистов",
    "priceMin": 17413,
    "priceMax": 239544,
    "unit": "за услугу",
    "duration": 7,
    "createdAt": "2023-07-31T21:00:00.000Z"
  },
  {
    "id": 73,
    "vendorId": 56,
    "name": "VIP транспорт",
    "category": "Транспорт",
    "description": "Профессиональная услуга \"Лимузин\" от опытных специалистов",
    "priceMin": 16486,
    "priceMax": 75879,
    "unit": "за час",
    "duration": 9,
    "createdAt": "2023-09-05T21:00:00.000Z"
  },
  {
    "id": 74,
    "vendorId": 56,
    "name": "Свадебный кортеж",
    "category": "Транспорт",
    "description": "Профессиональная услуга \"Лимузин\" от опытных специалистов",
    "priceMin": 9536,
    "priceMax": 204098,
    "unit": "за час",
    "duration": 3,
    "createdAt": "2023-12-01T21:00:00.000Z"
  },
  {
    "id": 75,
    "vendorId": 57,
    "name": "Караоке",
    "category": "Развлечения",
    "description": "Профессиональная услуга \"Аниматоры\" от опытных специалистов",
    "priceMin": 31312,
    "priceMax": 51843,
    "unit": "за услугу",
    "duration": 2,
    "createdAt": "2023-03-25T21:00:00.000Z"
  },
  {
    "id": 76,
    "vendorId": 57,
    "name": "Шоу-программа",
    "category": "Развлечения",
    "description": "Профессиональная услуга \"Ведущий\" от опытных специалистов",
    "priceMin": 35966,
    "priceMax": 175744,
    "unit": "за услугу",
    "duration": 4,
    "createdAt": "2023-02-19T21:00:00.000Z"
  },
  {
    "id": 77,
    "vendorId": 58,
    "name": "Живая музыка",
    "category": "Развлечения",
    "description": "Профессиональная услуга \"Караоке\" от опытных специалистов",
    "priceMin": 38633,
    "priceMax": 75918,
    "unit": "за час",
    "duration": 4,
    "createdAt": "2023-04-08T21:00:00.000Z"
  },
  {
    "id": 78,
    "vendorId": 58,
    "name": "Квест",
    "category": "Развлечения",
    "description": "Профессиональная услуга \"Квест\" от опытных специалистов",
    "priceMin": 45960,
    "priceMax": 188571,
    "unit": "за услугу",
    "duration": 4,
    "createdAt": "2023-01-26T21:00:00.000Z"
  },
  {
    "id": 79,
    "vendorId": 58,
    "name": "DJ",
    "category": "Развлечения",
    "description": "Профессиональная услуга \"Квест\" от опытных специалистов",
    "priceMin": 16542,
    "priceMax": 228583,
    "unit": "за услугу",
    "duration": 5,
    "createdAt": "2023-11-22T21:00:00.000Z"
  },
  {
    "id": 80,
    "vendorId": 58,
    "name": "Фото-видео зона",
    "category": "Развлечения",
    "description": "Профессиональная услуга \"Караоке\" от опытных специалистов",
    "priceMin": 52292,
    "priceMax": 142926,
    "unit": "за мероприятие",
    "duration": 9,
    "createdAt": "2023-12-12T21:00:00.000Z"
  },
  {
    "id": 81,
    "vendorId": 59,
    "name": "Фотозона",
    "category": "Декор",
    "description": "Профессиональная услуга \"Освещение\" от опытных специалистов",
    "priceMin": 30223,
    "priceMax": 231258,
    "unit": "за человека",
    "duration": 5,
    "createdAt": "2023-06-11T21:00:00.000Z"
  },
  {
    "id": 82,
    "vendorId": 59,
    "name": "Свадебная арка",
    "category": "Декор",
    "description": "Профессиональная услуга \"Освещение\" от опытных специалистов",
    "priceMin": 31333,
    "priceMax": 206473,
    "unit": "за мероприятие",
    "duration": 7,
    "createdAt": "2023-02-11T21:00:00.000Z"
  },
  {
    "id": 83,
    "vendorId": 59,
    "name": "Свадебная арка",
    "category": "Декор",
    "description": "Профессиональная услуга \"Освещение\" от опытных специалистов",
    "priceMin": 49355,
    "priceMax": 164100,
    "unit": "за услугу",
    "duration": 3,
    "createdAt": "2023-06-16T21:00:00.000Z"
  },
  {
    "id": 84,
    "vendorId": 60,
    "name": "Корпоративный обед",
    "category": "Кейтеринг",
    "description": "Профессиональная услуга \"Фуршет на 50 человек\" от опытных специалистов",
    "priceMin": 41439,
    "priceMax": 245525,
    "unit": "за человека",
    "duration": 7,
    "createdAt": "2023-05-27T21:00:00.000Z"
  },
  {
    "id": 85,
    "vendorId": 60,
    "name": "Банкет на 100 человек",
    "category": "Кейтеринг",
    "description": "Профессиональная услуга \"Фуршет на 50 человек\" от опытных специалистов",
    "priceMin": 11930,
    "priceMax": 83944,
    "unit": "за мероприятие",
    "duration": 6,
    "createdAt": "2023-06-17T21:00:00.000Z"
  },
  {
    "id": 86,
    "vendorId": 60,
    "name": "Корпоративный обед",
    "category": "Кейтеринг",
    "description": "Профессиональная услуга \"Канapé-сервис\" от опытных специалистов",
    "priceMin": 5564,
    "priceMax": 73914,
    "unit": "за услугу",
    "duration": 5,
    "createdAt": "2023-12-03T21:00:00.000Z"
  },
  {
    "id": 87,
    "vendorId": 60,
    "name": "Банкет на 100 человек",
    "category": "Кейтеринг",
    "description": "Профессиональная услуга \"Свадебный банкет\" от опытных специалистов",
    "priceMin": 27461,
    "priceMax": 241100,
    "unit": "за услугу",
    "duration": 7,
    "createdAt": "2023-06-05T21:00:00.000Z"
  },
  {
    "id": 88,
    "vendorId": 61,
    "name": "Оформление зала",
    "category": "Декор",
    "description": "Профессиональная услуга \"Фотозона\" от опытных специалистов",
    "priceMin": 40784,
    "priceMax": 230901,
    "unit": "за час",
    "duration": 9,
    "createdAt": "2023-11-23T21:00:00.000Z"
  },
  {
    "id": 89,
    "vendorId": 61,
    "name": "Фотозона",
    "category": "Декор",
    "description": "Профессиональная услуга \"Фотозона\" от опытных специалистов",
    "priceMin": 20991,
    "priceMax": 59923,
    "unit": "за человека",
    "duration": 5,
    "createdAt": "2023-07-06T21:00:00.000Z"
  },
  {
    "id": 90,
    "vendorId": 61,
    "name": "Свадебная арка",
    "category": "Декор",
    "description": "Профессиональная услуга \"Фотозона\" от опытных специалистов",
    "priceMin": 24433,
    "priceMax": 128833,
    "unit": "за час",
    "duration": 2,
    "createdAt": "2023-12-11T21:00:00.000Z"
  },
  {
    "id": 91,
    "vendorId": 62,
    "name": "Свадебная съемка",
    "category": "Фото и видео",
    "description": "Профессиональная услуга \"Промо-ролик\" от опытных специалистов",
    "priceMin": 9058,
    "priceMax": 73461,
    "unit": "за человека",
    "duration": 8,
    "createdAt": "2023-10-22T21:00:00.000Z"
  },
  {
    "id": 92,
    "vendorId": 62,
    "name": "Детская съемка",
    "category": "Фото и видео",
    "description": "Профессиональная услуга \"Свадебная съемка\" от опытных специалистов",
    "priceMin": 41775,
    "priceMax": 156371,
    "unit": "за час",
    "duration": 8,
    "createdAt": "2023-01-04T21:00:00.000Z"
  },
  {
    "id": 93,
    "vendorId": 62,
    "name": "Портретная съемка",
    "category": "Фото и видео",
    "description": "Профессиональная услуга \"Репортажная съемка\" от опытных специалистов",
    "priceMin": 44528,
    "priceMax": 140963,
    "unit": "за мероприятие",
    "duration": 4,
    "createdAt": "2023-05-24T21:00:00.000Z"
  },
  {
    "id": 94,
    "vendorId": 63,
    "name": "Дворец культуры",
    "category": "Площадки",
    "description": "Профессиональная услуга \"Дворец культуры\" от опытных специалистов",
    "priceMin": 31815,
    "priceMax": 91479,
    "unit": "за час",
    "duration": 2,
    "createdAt": "2023-02-01T21:00:00.000Z"
  },
  {
    "id": 95,
    "vendorId": 63,
    "name": "Банкетный зал",
    "category": "Площадки",
    "description": "Профессиональная услуга \"Лофт\" от опытных специалистов",
    "priceMin": 26278,
    "priceMax": 184882,
    "unit": "за час",
    "duration": 7,
    "createdAt": "2023-02-17T21:00:00.000Z"
  },
  {
    "id": 96,
    "vendorId": 64,
    "name": "Микроавтобус",
    "category": "Транспорт",
    "description": "Профессиональная услуга \"Автобус\" от опытных специалистов",
    "priceMin": 25109,
    "priceMax": 136833,
    "unit": "за человека",
    "duration": 2,
    "createdAt": "2023-06-30T21:00:00.000Z"
  },
  {
    "id": 97,
    "vendorId": 64,
    "name": "Свадебный кортеж",
    "category": "Транспорт",
    "description": "Профессиональная услуга \"VIP транспорт\" от опытных специалистов",
    "priceMin": 22019,
    "priceMax": 71749,
    "unit": "за человека",
    "duration": 5,
    "createdAt": "2023-05-23T21:00:00.000Z"
  },
  {
    "id": 98,
    "vendorId": 65,
    "name": "Видеоклип",
    "category": "Фото и видео",
    "description": "Профессиональная услуга \"Love Story\" от опытных специалистов",
    "priceMin": 13110,
    "priceMax": 248869,
    "unit": "за мероприятие",
    "duration": 7,
    "createdAt": "2023-01-10T21:00:00.000Z"
  },
  {
    "id": 99,
    "vendorId": 65,
    "name": "Корпоративная съемка",
    "category": "Фото и видео",
    "description": "Профессиональная услуга \"Промо-ролик\" от опытных специалистов",
    "priceMin": 40697,
    "priceMax": 104825,
    "unit": "за мероприятие",
    "duration": 2,
    "createdAt": "2023-07-02T21:00:00.000Z"
  },
  {
    "id": 100,
    "vendorId": 65,
    "name": "Корпоративная съемка",
    "category": "Фото и видео",
    "description": "Профессиональная услуга \"Детская съемка\" от опытных специалистов",
    "priceMin": 23145,
    "priceMax": 246055,
    "unit": "за человека",
    "duration": 9,
    "createdAt": "2023-11-02T21:00:00.000Z"
  },
  {
    "id": 101,
    "vendorId": 65,
    "name": "Видеоклип",
    "category": "Фото и видео",
    "description": "Профессиональная услуга \"Корпоративная съемка\" от опытных специалистов",
    "priceMin": 6226,
    "priceMax": 64919,
    "unit": "за час",
    "duration": 9,
    "createdAt": "2023-02-07T21:00:00.000Z"
  },
  {
    "id": 102,
    "vendorId": 66,
    "name": "Лимузин",
    "category": "Транспорт",
    "description": "Профессиональная услуга \"Автобус\" от опытных специалистов",
    "priceMin": 16448,
    "priceMax": 242986,
    "unit": "за человека",
    "duration": 6,
    "createdAt": "2023-09-02T21:00:00.000Z"
  },
  {
    "id": 103,
    "vendorId": 66,
    "name": "Автобус",
    "category": "Транспорт",
    "description": "Профессиональная услуга \"Экскурсионный автобус\" от опытных специалистов",
    "priceMin": 42923,
    "priceMax": 74284,
    "unit": "за час",
    "duration": 6,
    "createdAt": "2023-01-12T21:00:00.000Z"
  },
  {
    "id": 104,
    "vendorId": 66,
    "name": "Автобус",
    "category": "Транспорт",
    "description": "Профессиональная услуга \"Микроавтобус\" от опытных специалистов",
    "priceMin": 35645,
    "priceMax": 121911,
    "unit": "за час",
    "duration": 2,
    "createdAt": "2023-04-01T21:00:00.000Z"
  },
  {
    "id": 105,
    "vendorId": 67,
    "name": "Микроавтобус",
    "category": "Транспорт",
    "description": "Профессиональная услуга \"Микроавтобус\" от опытных специалистов",
    "priceMin": 23490,
    "priceMax": 66077,
    "unit": "за час",
    "duration": 2,
    "createdAt": "2023-09-13T21:00:00.000Z"
  },
  {
    "id": 106,
    "vendorId": 67,
    "name": "Лимузин",
    "category": "Транспорт",
    "description": "Профессиональная услуга \"Экскурсионный автобус\" от опытных специалистов",
    "priceMin": 27702,
    "priceMax": 176554,
    "unit": "за час",
    "duration": 6,
    "createdAt": "2023-06-14T21:00:00.000Z"
  },
  {
    "id": 107,
    "vendorId": 68,
    "name": "Кафе",
    "category": "Площадки",
    "description": "Профессиональная услуга \"Кафе\" от опытных специалистов",
    "priceMin": 26305,
    "priceMax": 143232,
    "unit": "за услугу",
    "duration": 8,
    "createdAt": "2023-08-07T21:00:00.000Z"
  },
  {
    "id": 108,
    "vendorId": 68,
    "name": "Загородный дом",
    "category": "Площадки",
    "description": "Профессиональная услуга \"Дворец культуры\" от опытных специалистов",
    "priceMin": 13645,
    "priceMax": 193549,
    "unit": "за час",
    "duration": 4,
    "createdAt": "2023-04-15T21:00:00.000Z"
  },
  {
    "id": 109,
    "vendorId": 68,
    "name": "Дворец культуры",
    "category": "Площадки",
    "description": "Профессиональная услуга \"Бар\" от опытных специалистов",
    "priceMin": 29618,
    "priceMax": 97375,
    "unit": "за человека",
    "duration": 6,
    "createdAt": "2023-10-16T21:00:00.000Z"
  },
  {
    "id": 110,
    "vendorId": 68,
    "name": "Бар",
    "category": "Площадки",
    "description": "Профессиональная услуга \"Терраса\" от опытных специалистов",
    "priceMin": 46849,
    "priceMax": 64903,
    "unit": "за час",
    "duration": 2,
    "createdAt": "2023-02-03T21:00:00.000Z"
  },
  {
    "id": 111,
    "vendorId": 69,
    "name": "Портретная съемка",
    "category": "Фото и видео",
    "description": "Профессиональная услуга \"Свадебная съемка\" от опытных специалистов",
    "priceMin": 47869,
    "priceMax": 194034,
    "unit": "за услугу",
    "duration": 6,
    "createdAt": "2023-08-10T21:00:00.000Z"
  },
  {
    "id": 112,
    "vendorId": 69,
    "name": "Промо-ролик",
    "category": "Фото и видео",
    "description": "Профессиональная услуга \"Портретная съемка\" от опытных специалистов",
    "priceMin": 42730,
    "priceMax": 145587,
    "unit": "за человека",
    "duration": 6,
    "createdAt": "2023-04-06T21:00:00.000Z"
  },
  {
    "id": 113,
    "vendorId": 70,
    "name": "Кофе-брейк",
    "category": "Кейтеринг",
    "description": "Профессиональная услуга \"Фуршет на 50 человек\" от опытных специалистов",
    "priceMin": 48731,
    "priceMax": 166139,
    "unit": "за мероприятие",
    "duration": 2,
    "createdAt": "2023-06-26T21:00:00.000Z"
  },
  {
    "id": 114,
    "vendorId": 70,
    "name": "Барбекю",
    "category": "Кейтеринг",
    "description": "Профессиональная услуга \"Свадебный банкет\" от опытных специалистов",
    "priceMin": 27117,
    "priceMax": 231423,
    "unit": "за час",
    "duration": 2,
    "createdAt": "2023-05-16T21:00:00.000Z"
  },
  {
    "id": 115,
    "vendorId": 70,
    "name": "Кофе-брейк",
    "category": "Кейтеринг",
    "description": "Профессиональная услуга \"Барбекю\" от опытных специалистов",
    "priceMin": 42424,
    "priceMax": 152384,
    "unit": "за мероприятие",
    "duration": 7,
    "createdAt": "2023-11-01T21:00:00.000Z"
  },
  {
    "id": 116,
    "vendorId": 70,
    "name": "Шведский стол",
    "category": "Кейтеринг",
    "description": "Профессиональная услуга \"Корпоративный обед\" от опытных специалистов",
    "priceMin": 27577,
    "priceMax": 63704,
    "unit": "за мероприятие",
    "duration": 5,
    "createdAt": "2023-12-23T21:00:00.000Z"
  },
  {
    "id": 117,
    "vendorId": 71,
    "name": "Оформление зала",
    "category": "Декор",
    "description": "Профессиональная услуга \"Текстиль\" от опытных специалистов",
    "priceMin": 24999,
    "priceMax": 242967,
    "unit": "за мероприятие",
    "duration": 2,
    "createdAt": "2023-02-10T21:00:00.000Z"
  },
  {
    "id": 118,
    "vendorId": 71,
    "name": "Освещение",
    "category": "Декор",
    "description": "Профессиональная услуга \"Цветочная арка\" от опытных специалистов",
    "priceMin": 37610,
    "priceMax": 144250,
    "unit": "за мероприятие",
    "duration": 7,
    "createdAt": "2023-12-24T21:00:00.000Z"
  },
  {
    "id": 119,
    "vendorId": 71,
    "name": "Баннеры",
    "category": "Декор",
    "description": "Профессиональная услуга \"Текстиль\" от опытных специалистов",
    "priceMin": 45818,
    "priceMax": 151087,
    "unit": "за мероприятие",
    "duration": 4,
    "createdAt": "2023-09-17T21:00:00.000Z"
  },
  {
    "id": 120,
    "vendorId": 72,
    "name": "Фуршет на 50 человек",
    "category": "Кейтеринг",
    "description": "Профессиональная услуга \"Банкет на 100 человек\" от опытных специалистов",
    "priceMin": 53456,
    "priceMax": 144591,
    "unit": "за человека",
    "duration": 2,
    "createdAt": "2023-04-04T21:00:00.000Z"
  },
  {
    "id": 121,
    "vendorId": 72,
    "name": "Канapé-сервис",
    "category": "Кейтеринг",
    "description": "Профессиональная услуга \"Барбекю\" от опытных специалистов",
    "priceMin": 47983,
    "priceMax": 175040,
    "unit": "за мероприятие",
    "duration": 3,
    "createdAt": "2023-02-18T21:00:00.000Z"
  },
  {
    "id": 122,
    "vendorId": 72,
    "name": "Банкет на 100 человек",
    "category": "Кейтеринг",
    "description": "Профессиональная услуга \"Корпоративный обед\" от опытных специалистов",
    "priceMin": 35136,
    "priceMax": 157331,
    "unit": "за услугу",
    "duration": 9,
    "createdAt": "2023-05-31T21:00:00.000Z"
  },
  {
    "id": 123,
    "vendorId": 72,
    "name": "Корпоративный обед",
    "category": "Кейтеринг",
    "description": "Профессиональная услуга \"Фуршет на 50 человек\" от опытных специалистов",
    "priceMin": 12410,
    "priceMax": 236668,
    "unit": "за мероприятие",
    "duration": 7,
    "createdAt": "2023-11-15T21:00:00.000Z"
  },
  {
    "id": 124,
    "vendorId": 73,
    "name": "Свадебная съемка",
    "category": "Фото и видео",
    "description": "Профессиональная услуга \"Репортажная съемка\" от опытных специалистов",
    "priceMin": 16670,
    "priceMax": 197630,
    "unit": "за мероприятие",
    "duration": 5,
    "createdAt": "2023-06-13T21:00:00.000Z"
  },
  {
    "id": 125,
    "vendorId": 73,
    "name": "Промо-ролик",
    "category": "Фото и видео",
    "description": "Профессиональная услуга \"Портретная съемка\" от опытных специалистов",
    "priceMin": 54634,
    "priceMax": 164420,
    "unit": "за мероприятие",
    "duration": 5,
    "createdAt": "2023-11-14T21:00:00.000Z"
  },
  {
    "id": 126,
    "vendorId": 74,
    "name": "Портретная съемка",
    "category": "Фото и видео",
    "description": "Профессиональная услуга \"Видеоклип\" от опытных специалистов",
    "priceMin": 22764,
    "priceMax": 179839,
    "unit": "за час",
    "duration": 6,
    "createdAt": "2023-02-17T21:00:00.000Z"
  },
  {
    "id": 127,
    "vendorId": 74,
    "name": "Детская съемка",
    "category": "Фото и видео",
    "description": "Профессиональная услуга \"Портретная съемка\" от опытных специалистов",
    "priceMin": 29288,
    "priceMax": 67247,
    "unit": "за мероприятие",
    "duration": 9,
    "createdAt": "2023-09-19T21:00:00.000Z"
  },
  {
    "id": 128,
    "vendorId": 75,
    "name": "Кафе",
    "category": "Площадки",
    "description": "Профессиональная услуга \"Лофт\" от опытных специалистов",
    "priceMin": 18917,
    "priceMax": 140677,
    "unit": "за человека",
    "duration": 7,
    "createdAt": "2023-03-04T21:00:00.000Z"
  },
  {
    "id": 129,
    "vendorId": 75,
    "name": "Загородный дом",
    "category": "Площадки",
    "description": "Профессиональная услуга \"Банкетный зал\" от опытных специалистов",
    "priceMin": 21399,
    "priceMax": 247792,
    "unit": "за услугу",
    "duration": 7,
    "createdAt": "2023-08-05T21:00:00.000Z"
  },
  {
    "id": 130,
    "vendorId": 75,
    "name": "Бар",
    "category": "Площадки",
    "description": "Профессиональная услуга \"Терраса\" от опытных специалистов",
    "priceMin": 41862,
    "priceMax": 212584,
    "unit": "за человека",
    "duration": 5,
    "createdAt": "2023-11-18T21:00:00.000Z"
  },
  {
    "id": 131,
    "vendorId": 75,
    "name": "Ресторан",
    "category": "Площадки",
    "description": "Профессиональная услуга \"Кафе\" от опытных специалистов",
    "priceMin": 35201,
    "priceMax": 229089,
    "unit": "за мероприятие",
    "duration": 7,
    "createdAt": "2023-01-31T21:00:00.000Z"
  },
  {
    "id": 132,
    "vendorId": 76,
    "name": "Love Story",
    "category": "Фото и видео",
    "description": "Профессиональная услуга \"Видеоклип\" от опытных специалистов",
    "priceMin": 32761,
    "priceMax": 134386,
    "unit": "за час",
    "duration": 7,
    "createdAt": "2023-04-17T21:00:00.000Z"
  },
  {
    "id": 133,
    "vendorId": 76,
    "name": "Видеоклип",
    "category": "Фото и видео",
    "description": "Профессиональная услуга \"Портретная съемка\" от опытных специалистов",
    "priceMin": 37809,
    "priceMax": 239704,
    "unit": "за услугу",
    "duration": 7,
    "createdAt": "2023-02-17T21:00:00.000Z"
  },
  {
    "id": 134,
    "vendorId": 77,
    "name": "Детская съемка",
    "category": "Фото и видео",
    "description": "Профессиональная услуга \"Корпоративная съемка\" от опытных специалистов",
    "priceMin": 51838,
    "priceMax": 248200,
    "unit": "за услугу",
    "duration": 7,
    "createdAt": "2023-05-02T21:00:00.000Z"
  },
  {
    "id": 135,
    "vendorId": 77,
    "name": "Детская съемка",
    "category": "Фото и видео",
    "description": "Профессиональная услуга \"Репортажная съемка\" от опытных специалистов",
    "priceMin": 51417,
    "priceMax": 120180,
    "unit": "за мероприятие",
    "duration": 4,
    "createdAt": "2022-12-31T21:00:00.000Z"
  },
  {
    "id": 136,
    "vendorId": 78,
    "name": "Корпоративный обед",
    "category": "Кейтеринг",
    "description": "Профессиональная услуга \"Фуршет на 50 человек\" от опытных специалистов",
    "priceMin": 50864,
    "priceMax": 140010,
    "unit": "за услугу",
    "duration": 5,
    "createdAt": "2023-04-10T21:00:00.000Z"
  },
  {
    "id": 137,
    "vendorId": 78,
    "name": "Банкет на 100 человек",
    "category": "Кейтеринг",
    "description": "Профессиональная услуга \"Банкет на 100 человек\" от опытных специалистов",
    "priceMin": 10169,
    "priceMax": 121605,
    "unit": "за мероприятие",
    "duration": 8,
    "createdAt": "2023-04-30T21:00:00.000Z"
  },
  {
    "id": 138,
    "vendorId": 79,
    "name": "Лимузин",
    "category": "Транспорт",
    "description": "Профессиональная услуга \"Лимузин\" от опытных специалистов",
    "priceMin": 25712,
    "priceMax": 249014,
    "unit": "за час",
    "duration": 9,
    "createdAt": "2023-11-22T21:00:00.000Z"
  },
  {
    "id": 139,
    "vendorId": 79,
    "name": "Автобус",
    "category": "Транспорт",
    "description": "Профессиональная услуга \"Свадебный кортеж\" от опытных специалистов",
    "priceMin": 9475,
    "priceMax": 85946,
    "unit": "за мероприятие",
    "duration": 9,
    "createdAt": "2023-11-26T21:00:00.000Z"
  },
  {
    "id": 140,
    "vendorId": 79,
    "name": "Свадебный кортеж",
    "category": "Транспорт",
    "description": "Профессиональная услуга \"Автобус\" от опытных специалистов",
    "priceMin": 16073,
    "priceMax": 174377,
    "unit": "за час",
    "duration": 2,
    "createdAt": "2023-09-21T21:00:00.000Z"
  },
  {
    "id": 141,
    "vendorId": 80,
    "name": "Канapé-сервис",
    "category": "Кейтеринг",
    "description": "Профессиональная услуга \"Фуршет на 50 человек\" от опытных специалистов",
    "priceMin": 38259,
    "priceMax": 202278,
    "unit": "за мероприятие",
    "duration": 8,
    "createdAt": "2023-10-11T21:00:00.000Z"
  },
  {
    "id": 142,
    "vendorId": 80,
    "name": "Кофе-брейк",
    "category": "Кейтеринг",
    "description": "Профессиональная услуга \"Фуршет на 50 человек\" от опытных специалистов",
    "priceMin": 5837,
    "priceMax": 83185,
    "unit": "за человека",
    "duration": 9,
    "createdAt": "2023-04-13T21:00:00.000Z"
  },
  {
    "id": 143,
    "vendorId": 80,
    "name": "Барбекю",
    "category": "Кейтеринг",
    "description": "Профессиональная услуга \"Банкет на 100 человек\" от опытных специалистов",
    "priceMin": 41512,
    "priceMax": 202369,
    "unit": "за мероприятие",
    "duration": 5,
    "createdAt": "2023-07-13T21:00:00.000Z"
  },
  {
    "id": 144,
    "vendorId": 81,
    "name": "Свадебный кортеж",
    "category": "Транспорт",
    "description": "Профессиональная услуга \"Автобус\" от опытных специалистов",
    "priceMin": 15485,
    "priceMax": 75347,
    "unit": "за услугу",
    "duration": 5,
    "createdAt": "2023-05-12T21:00:00.000Z"
  },
  {
    "id": 145,
    "vendorId": 81,
    "name": "Лимузин",
    "category": "Транспорт",
    "description": "Профессиональная услуга \"Лимузин\" от опытных специалистов",
    "priceMin": 33766,
    "priceMax": 172796,
    "unit": "за человека",
    "duration": 8,
    "createdAt": "2023-10-05T21:00:00.000Z"
  },
  {
    "id": 146,
    "vendorId": 82,
    "name": "Корпоративный обед",
    "category": "Кейтеринг",
    "description": "Профессиональная услуга \"Корпоративный обед\" от опытных специалистов",
    "priceMin": 41911,
    "priceMax": 190058,
    "unit": "за человека",
    "duration": 8,
    "createdAt": "2023-02-09T21:00:00.000Z"
  },
  {
    "id": 147,
    "vendorId": 82,
    "name": "Фуршет на 50 человек",
    "category": "Кейтеринг",
    "description": "Профессиональная услуга \"Банкет на 100 человек\" от опытных специалистов",
    "priceMin": 6768,
    "priceMax": 54185,
    "unit": "за мероприятие",
    "duration": 6,
    "createdAt": "2023-07-10T21:00:00.000Z"
  },
  {
    "id": 148,
    "vendorId": 82,
    "name": "Барбекю",
    "category": "Кейтеринг",
    "description": "Профессиональная услуга \"Кофе-брейк\" от опытных специалистов",
    "priceMin": 34916,
    "priceMax": 162297,
    "unit": "за мероприятие",
    "duration": 2,
    "createdAt": "2023-05-27T21:00:00.000Z"
  },
  {
    "id": 149,
    "vendorId": 82,
    "name": "Корпоративный обед",
    "category": "Кейтеринг",
    "description": "Профессиональная услуга \"Фуршет на 50 человек\" от опытных специалистов",
    "priceMin": 13347,
    "priceMax": 216156,
    "unit": "за услугу",
    "duration": 9,
    "createdAt": "2023-07-07T21:00:00.000Z"
  },
  {
    "id": 150,
    "vendorId": 83,
    "name": "Свадебная съемка",
    "category": "Фото и видео",
    "description": "Профессиональная услуга \"Детская съемка\" от опытных специалистов",
    "priceMin": 17028,
    "priceMax": 135333,
    "unit": "за человека",
    "duration": 9,
    "createdAt": "2023-03-09T21:00:00.000Z"
  },
  {
    "id": 151,
    "vendorId": 83,
    "name": "Промо-ролик",
    "category": "Фото и видео",
    "description": "Профессиональная услуга \"Свадебная съемка\" от опытных специалистов",
    "priceMin": 8410,
    "priceMax": 69852,
    "unit": "за час",
    "duration": 6,
    "createdAt": "2023-10-07T21:00:00.000Z"
  },
  {
    "id": 152,
    "vendorId": 83,
    "name": "Видеоклип",
    "category": "Фото и видео",
    "description": "Профессиональная услуга \"Репортажная съемка\" от опытных специалистов",
    "priceMin": 30531,
    "priceMax": 62326,
    "unit": "за мероприятие",
    "duration": 9,
    "createdAt": "2023-12-12T21:00:00.000Z"
  },
  {
    "id": 153,
    "vendorId": 83,
    "name": "Детская съемка",
    "category": "Фото и видео",
    "description": "Профессиональная услуга \"Промо-ролик\" от опытных специалистов",
    "priceMin": 44461,
    "priceMax": 192907,
    "unit": "за час",
    "duration": 8,
    "createdAt": "2023-01-12T21:00:00.000Z"
  },
  {
    "id": 154,
    "vendorId": 84,
    "name": "Караоке",
    "category": "Развлечения",
    "description": "Профессиональная услуга \"Фото-видео зона\" от опытных специалистов",
    "priceMin": 48705,
    "priceMax": 238930,
    "unit": "за час",
    "duration": 7,
    "createdAt": "2023-05-06T21:00:00.000Z"
  },
  {
    "id": 155,
    "vendorId": 84,
    "name": "Аниматоры",
    "category": "Развлечения",
    "description": "Профессиональная услуга \"Шоу-программа\" от опытных специалистов",
    "priceMin": 20576,
    "priceMax": 138970,
    "unit": "за час",
    "duration": 5,
    "createdAt": "2023-09-22T21:00:00.000Z"
  },
  {
    "id": 156,
    "vendorId": 84,
    "name": "Фото-видео зона",
    "category": "Развлечения",
    "description": "Профессиональная услуга \"Аниматоры\" от опытных специалистов",
    "priceMin": 20742,
    "priceMax": 143285,
    "unit": "за услугу",
    "duration": 6,
    "createdAt": "2023-11-04T21:00:00.000Z"
  },
  {
    "id": 157,
    "vendorId": 84,
    "name": "Аниматоры",
    "category": "Развлечения",
    "description": "Профессиональная услуга \"Ведущий\" от опытных специалистов",
    "priceMin": 51427,
    "priceMax": 166413,
    "unit": "за час",
    "duration": 9,
    "createdAt": "2023-07-02T21:00:00.000Z"
  },
  {
    "id": 158,
    "vendorId": 85,
    "name": "Ресторан",
    "category": "Площадки",
    "description": "Профессиональная услуга \"Дворец культуры\" от опытных специалистов",
    "priceMin": 20394,
    "priceMax": 219767,
    "unit": "за час",
    "duration": 9,
    "createdAt": "2023-06-12T21:00:00.000Z"
  },
  {
    "id": 159,
    "vendorId": 85,
    "name": "Ресторан",
    "category": "Площадки",
    "description": "Профессиональная услуга \"Терраса\" от опытных специалистов",
    "priceMin": 19841,
    "priceMax": 182542,
    "unit": "за человека",
    "duration": 8,
    "createdAt": "2023-02-09T21:00:00.000Z"
  },
  {
    "id": 160,
    "vendorId": 85,
    "name": "Ресторан",
    "category": "Площадки",
    "description": "Профессиональная услуга \"Терраса\" от опытных специалистов",
    "priceMin": 22872,
    "priceMax": 215444,
    "unit": "за человека",
    "duration": 6,
    "createdAt": "2023-01-31T21:00:00.000Z"
  },
  {
    "id": 161,
    "vendorId": 85,
    "name": "Ресторан",
    "category": "Площадки",
    "description": "Профессиональная услуга \"Загородный дом\" от опытных специалистов",
    "priceMin": 16639,
    "priceMax": 115289,
    "unit": "за человека",
    "duration": 5,
    "createdAt": "2023-04-30T21:00:00.000Z"
  },
  {
    "id": 162,
    "vendorId": 86,
    "name": "VIP транспорт",
    "category": "Транспорт",
    "description": "Профессиональная услуга \"Лимузин\" от опытных специалистов",
    "priceMin": 10912,
    "priceMax": 179894,
    "unit": "за услугу",
    "duration": 8,
    "createdAt": "2023-04-11T21:00:00.000Z"
  },
  {
    "id": 163,
    "vendorId": 86,
    "name": "Свадебный кортеж",
    "category": "Транспорт",
    "description": "Профессиональная услуга \"Экскурсионный автобус\" от опытных специалистов",
    "priceMin": 12367,
    "priceMax": 203912,
    "unit": "за человека",
    "duration": 8,
    "createdAt": "2023-07-06T21:00:00.000Z"
  },
  {
    "id": 164,
    "vendorId": 86,
    "name": "Лимузин",
    "category": "Транспорт",
    "description": "Профессиональная услуга \"Экскурсионный автобус\" от опытных специалистов",
    "priceMin": 9988,
    "priceMax": 173648,
    "unit": "за час",
    "duration": 2,
    "createdAt": "2023-03-18T21:00:00.000Z"
  },
  {
    "id": 165,
    "vendorId": 86,
    "name": "VIP транспорт",
    "category": "Транспорт",
    "description": "Профессиональная услуга \"Свадебный кортеж\" от опытных специалистов",
    "priceMin": 41239,
    "priceMax": 121510,
    "unit": "за мероприятие",
    "duration": 5,
    "createdAt": "2023-04-17T21:00:00.000Z"
  },
  {
    "id": 166,
    "vendorId": 87,
    "name": "Освещение",
    "category": "Декор",
    "description": "Профессиональная услуга \"Свадебная арка\" от опытных специалистов",
    "priceMin": 41742,
    "priceMax": 76944,
    "unit": "за человека",
    "duration": 8,
    "createdAt": "2023-02-28T21:00:00.000Z"
  },
  {
    "id": 167,
    "vendorId": 87,
    "name": "Свечи",
    "category": "Декор",
    "description": "Профессиональная услуга \"Освещение\" от опытных специалистов",
    "priceMin": 43495,
    "priceMax": 168877,
    "unit": "за мероприятие",
    "duration": 6,
    "createdAt": "2023-04-11T21:00:00.000Z"
  },
  {
    "id": 168,
    "vendorId": 87,
    "name": "Фотозона",
    "category": "Декор",
    "description": "Профессиональная услуга \"Свечи\" от опытных специалистов",
    "priceMin": 28643,
    "priceMax": 153043,
    "unit": "за человека",
    "duration": 5,
    "createdAt": "2023-02-10T21:00:00.000Z"
  },
  {
    "id": 169,
    "vendorId": 88,
    "name": "Видеоклип",
    "category": "Фото и видео",
    "description": "Профессиональная услуга \"Промо-ролик\" от опытных специалистов",
    "priceMin": 14746,
    "priceMax": 209929,
    "unit": "за мероприятие",
    "duration": 4,
    "createdAt": "2023-03-25T21:00:00.000Z"
  },
  {
    "id": 170,
    "vendorId": 88,
    "name": "Видеоклип",
    "category": "Фото и видео",
    "description": "Профессиональная услуга \"Love Story\" от опытных специалистов",
    "priceMin": 48713,
    "priceMax": 151768,
    "unit": "за услугу",
    "duration": 8,
    "createdAt": "2023-08-12T21:00:00.000Z"
  },
  {
    "id": 171,
    "vendorId": 89,
    "name": "Автобус",
    "category": "Транспорт",
    "description": "Профессиональная услуга \"VIP транспорт\" от опытных специалистов",
    "priceMin": 26825,
    "priceMax": 187132,
    "unit": "за час",
    "duration": 6,
    "createdAt": "2023-12-04T21:00:00.000Z"
  },
  {
    "id": 172,
    "vendorId": 89,
    "name": "Свадебный кортеж",
    "category": "Транспорт",
    "description": "Профессиональная услуга \"Лимузин\" от опытных специалистов",
    "priceMin": 37318,
    "priceMax": 68855,
    "unit": "за мероприятие",
    "duration": 6,
    "createdAt": "2023-11-15T21:00:00.000Z"
  },
  {
    "id": 173,
    "vendorId": 90,
    "name": "Банкет на 100 человек",
    "category": "Кейтеринг",
    "description": "Профессиональная услуга \"Барбекю\" от опытных специалистов",
    "priceMin": 12279,
    "priceMax": 177168,
    "unit": "за услугу",
    "duration": 6,
    "createdAt": "2023-03-01T21:00:00.000Z"
  },
  {
    "id": 174,
    "vendorId": 90,
    "name": "Кофе-брейк",
    "category": "Кейтеринг",
    "description": "Профессиональная услуга \"Канapé-сервис\" от опытных специалистов",
    "priceMin": 12875,
    "priceMax": 113400,
    "unit": "за услугу",
    "duration": 5,
    "createdAt": "2023-02-11T21:00:00.000Z"
  },
  {
    "id": 175,
    "vendorId": 90,
    "name": "Кофе-брейк",
    "category": "Кейтеринг",
    "description": "Профессиональная услуга \"Фуршет на 50 человек\" от опытных специалистов",
    "priceMin": 22831,
    "priceMax": 247386,
    "unit": "за услугу",
    "duration": 3,
    "createdAt": "2023-11-27T21:00:00.000Z"
  },
  {
    "id": 176,
    "vendorId": 90,
    "name": "Банкет на 100 человек",
    "category": "Кейтеринг",
    "description": "Профессиональная услуга \"Свадебный банкет\" от опытных специалистов",
    "priceMin": 32667,
    "priceMax": 143654,
    "unit": "за услугу",
    "duration": 6,
    "createdAt": "2023-07-01T21:00:00.000Z"
  },
  {
    "id": 177,
    "vendorId": 91,
    "name": "Банкет на 100 человек",
    "category": "Кейтеринг",
    "description": "Профессиональная услуга \"Шведский стол\" от опытных специалистов",
    "priceMin": 14397,
    "priceMax": 171883,
    "unit": "за человека",
    "duration": 4,
    "createdAt": "2023-08-08T21:00:00.000Z"
  },
  {
    "id": 178,
    "vendorId": 91,
    "name": "Барбекю",
    "category": "Кейтеринг",
    "description": "Профессиональная услуга \"Барбекю\" от опытных специалистов",
    "priceMin": 5466,
    "priceMax": 114639,
    "unit": "за час",
    "duration": 5,
    "createdAt": "2023-04-30T21:00:00.000Z"
  },
  {
    "id": 179,
    "vendorId": 91,
    "name": "Корпоративный обед",
    "category": "Кейтеринг",
    "description": "Профессиональная услуга \"Свадебный банкет\" от опытных специалистов",
    "priceMin": 20037,
    "priceMax": 60981,
    "unit": "за человека",
    "duration": 9,
    "createdAt": "2023-04-19T21:00:00.000Z"
  },
  {
    "id": 180,
    "vendorId": 92,
    "name": "Ведущий",
    "category": "Развлечения",
    "description": "Профессиональная услуга \"Живая музыка\" от опытных специалистов",
    "priceMin": 27162,
    "priceMax": 222713,
    "unit": "за услугу",
    "duration": 9,
    "createdAt": "2023-01-24T21:00:00.000Z"
  },
  {
    "id": 181,
    "vendorId": 92,
    "name": "Шоу-программа",
    "category": "Развлечения",
    "description": "Профессиональная услуга \"DJ\" от опытных специалистов",
    "priceMin": 20302,
    "priceMax": 83765,
    "unit": "за человека",
    "duration": 4,
    "createdAt": "2023-06-18T21:00:00.000Z"
  },
  {
    "id": 182,
    "vendorId": 92,
    "name": "Аниматоры",
    "category": "Развлечения",
    "description": "Профессиональная услуга \"Фото-видео зона\" от опытных специалистов",
    "priceMin": 23659,
    "priceMax": 209986,
    "unit": "за мероприятие",
    "duration": 5,
    "createdAt": "2023-08-17T21:00:00.000Z"
  },
  {
    "id": 183,
    "vendorId": 93,
    "name": "Банкет на 100 человек",
    "category": "Кейтеринг",
    "description": "Профессиональная услуга \"Барбекю\" от опытных специалистов",
    "priceMin": 20350,
    "priceMax": 220317,
    "unit": "за услугу",
    "duration": 6,
    "createdAt": "2023-03-19T21:00:00.000Z"
  },
  {
    "id": 184,
    "vendorId": 93,
    "name": "Кофе-брейк",
    "category": "Кейтеринг",
    "description": "Профессиональная услуга \"Корпоративный обед\" от опытных специалистов",
    "priceMin": 25129,
    "priceMax": 240875,
    "unit": "за час",
    "duration": 4,
    "createdAt": "2023-06-22T21:00:00.000Z"
  },
  {
    "id": 185,
    "vendorId": 94,
    "name": "Живая музыка",
    "category": "Развлечения",
    "description": "Профессиональная услуга \"Шоу-программа\" от опытных специалистов",
    "priceMin": 32972,
    "priceMax": 115981,
    "unit": "за человека",
    "duration": 2,
    "createdAt": "2023-10-19T21:00:00.000Z"
  },
  {
    "id": 186,
    "vendorId": 94,
    "name": "Квест",
    "category": "Развлечения",
    "description": "Профессиональная услуга \"Аниматоры\" от опытных специалистов",
    "priceMin": 36861,
    "priceMax": 119064,
    "unit": "за мероприятие",
    "duration": 7,
    "createdAt": "2023-05-15T21:00:00.000Z"
  },
  {
    "id": 187,
    "vendorId": 94,
    "name": "Живая музыка",
    "category": "Развлечения",
    "description": "Профессиональная услуга \"Ведущий\" от опытных специалистов",
    "priceMin": 23713,
    "priceMax": 111157,
    "unit": "за мероприятие",
    "duration": 7,
    "createdAt": "2023-11-11T21:00:00.000Z"
  },
  {
    "id": 188,
    "vendorId": 95,
    "name": "Цветочная арка",
    "category": "Декор",
    "description": "Профессиональная услуга \"Свадебная арка\" от опытных специалистов",
    "priceMin": 51509,
    "priceMax": 110698,
    "unit": "за час",
    "duration": 3,
    "createdAt": "2023-07-14T21:00:00.000Z"
  },
  {
    "id": 189,
    "vendorId": 95,
    "name": "Фотозона",
    "category": "Декор",
    "description": "Профессиональная услуга \"Свадебная арка\" от опытных специалистов",
    "priceMin": 26349,
    "priceMax": 94485,
    "unit": "за человека",
    "duration": 5,
    "createdAt": "2023-10-27T21:00:00.000Z"
  },
  {
    "id": 190,
    "vendorId": 96,
    "name": "Баннеры",
    "category": "Декор",
    "description": "Профессиональная услуга \"Фотозона\" от опытных специалистов",
    "priceMin": 5154,
    "priceMax": 141565,
    "unit": "за человека",
    "duration": 2,
    "createdAt": "2023-08-10T21:00:00.000Z"
  },
  {
    "id": 191,
    "vendorId": 96,
    "name": "Освещение",
    "category": "Декор",
    "description": "Профессиональная услуга \"Свадебная арка\" от опытных специалистов",
    "priceMin": 11716,
    "priceMax": 58389,
    "unit": "за мероприятие",
    "duration": 7,
    "createdAt": "2023-03-01T21:00:00.000Z"
  },
  {
    "id": 192,
    "vendorId": 96,
    "name": "Оформление зала",
    "category": "Декор",
    "description": "Профессиональная услуга \"Баннеры\" от опытных специалистов",
    "priceMin": 54739,
    "priceMax": 96575,
    "unit": "за час",
    "duration": 7,
    "createdAt": "2023-05-07T21:00:00.000Z"
  },
  {
    "id": 193,
    "vendorId": 97,
    "name": "Шведский стол",
    "category": "Кейтеринг",
    "description": "Профессиональная услуга \"Канapé-сервис\" от опытных специалистов",
    "priceMin": 29491,
    "priceMax": 73827,
    "unit": "за услугу",
    "duration": 3,
    "createdAt": "2023-06-26T21:00:00.000Z"
  },
  {
    "id": 194,
    "vendorId": 97,
    "name": "Барбекю",
    "category": "Кейтеринг",
    "description": "Профессиональная услуга \"Банкет на 100 человек\" от опытных специалистов",
    "priceMin": 35728,
    "priceMax": 128909,
    "unit": "за мероприятие",
    "duration": 8,
    "createdAt": "2023-03-03T21:00:00.000Z"
  },
  {
    "id": 195,
    "vendorId": 97,
    "name": "Шведский стол",
    "category": "Кейтеринг",
    "description": "Профессиональная услуга \"Корпоративный обед\" от опытных специалистов",
    "priceMin": 13125,
    "priceMax": 125247,
    "unit": "за человека",
    "duration": 2,
    "createdAt": "2023-03-08T21:00:00.000Z"
  },
  {
    "id": 196,
    "vendorId": 98,
    "name": "Фотозона",
    "category": "Декор",
    "description": "Профессиональная услуга \"Свадебная арка\" от опытных специалистов",
    "priceMin": 33173,
    "priceMax": 121444,
    "unit": "за услугу",
    "duration": 9,
    "createdAt": "2023-04-19T21:00:00.000Z"
  },
  {
    "id": 197,
    "vendorId": 98,
    "name": "Фотозона",
    "category": "Декор",
    "description": "Профессиональная услуга \"Оформление зала\" от опытных специалистов",
    "priceMin": 35815,
    "priceMax": 50601,
    "unit": "за человека",
    "duration": 2,
    "createdAt": "2023-02-13T21:00:00.000Z"
  },
  {
    "id": 198,
    "vendorId": 98,
    "name": "Баннеры",
    "category": "Декор",
    "description": "Профессиональная услуга \"Освещение\" от опытных специалистов",
    "priceMin": 25533,
    "priceMax": 110404,
    "unit": "за мероприятие",
    "duration": 6,
    "createdAt": "2023-02-09T21:00:00.000Z"
  },
  {
    "id": 199,
    "vendorId": 98,
    "name": "Свадебная арка",
    "category": "Декор",
    "description": "Профессиональная услуга \"Цветочная арка\" от опытных специалистов",
    "priceMin": 5144,
    "priceMax": 136039,
    "unit": "за услугу",
    "duration": 2,
    "createdAt": "2023-11-09T21:00:00.000Z"
  },
  {
    "id": 200,
    "vendorId": 99,
    "name": "Фото-видео зона",
    "category": "Развлечения",
    "description": "Профессиональная услуга \"Квест\" от опытных специалистов",
    "priceMin": 32582,
    "priceMax": 175379,
    "unit": "за услугу",
    "duration": 4,
    "createdAt": "2023-06-09T21:00:00.000Z"
  },
  {
    "id": 201,
    "vendorId": 99,
    "name": "Фото-видео зона",
    "category": "Развлечения",
    "description": "Профессиональная услуга \"Караоке\" от опытных специалистов",
    "priceMin": 13152,
    "priceMax": 147246,
    "unit": "за мероприятие",
    "duration": 6,
    "createdAt": "2023-09-12T21:00:00.000Z"
  },
  {
    "id": 202,
    "vendorId": 99,
    "name": "Аниматоры",
    "category": "Развлечения",
    "description": "Профессиональная услуга \"Ведущий\" от опытных специалистов",
    "priceMin": 54456,
    "priceMax": 195703,
    "unit": "за человека",
    "duration": 2,
    "createdAt": "2023-03-03T21:00:00.000Z"
  },
  {
    "id": 203,
    "vendorId": 100,
    "name": "Свадебный кортеж",
    "category": "Транспорт",
    "description": "Профессиональная услуга \"VIP транспорт\" от опытных специалистов",
    "priceMin": 22809,
    "priceMax": 167952,
    "unit": "за услугу",
    "duration": 8,
    "createdAt": "2023-04-17T21:00:00.000Z"
  },
  {
    "id": 204,
    "vendorId": 100,
    "name": "VIP транспорт",
    "category": "Транспорт",
    "description": "Профессиональная услуга \"Экскурсионный автобус\" от опытных специалистов",
    "priceMin": 24880,
    "priceMax": 128339,
    "unit": "за человека",
    "duration": 5,
    "createdAt": "2023-09-18T21:00:00.000Z"
  },
  {
    "id": 205,
    "vendorId": 100,
    "name": "Микроавтобус",
    "category": "Транспорт",
    "description": "Профессиональная услуга \"Лимузин\" от опытных специалистов",
    "priceMin": 15064,
    "priceMax": 65017,
    "unit": "за человека",
    "duration": 9,
    "createdAt": "2023-10-01T21:00:00.000Z"
  }
]